LICENSE
MANIFEST.in
README.md
pyproject.toml
requirements.txt
setup.cfg
setup.py
torchyolo/__init__.py
torchyolo/automodel.py
torchyolo/cli.py
torchyolo/predict.py
torchyolo.egg-info/PKG-INFO
torchyolo.egg-info/SOURCES.txt
torchyolo.egg-info/dependency_links.txt
torchyolo.egg-info/entry_points.txt
torchyolo.egg-info/requires.txt
torchyolo.egg-info/top_level.txt
torchyolo/configs/__init__.py
torchyolo/configs/tracker/__init__.py
torchyolo/modelhub/__init__.py
torchyolo/modelhub/yolov5.py
torchyolo/modelhub/yolov6.py
torchyolo/modelhub/yolov7.py
torchyolo/modelhub/yolov8.py
torchyolo/tracker/__init__.py
torchyolo/tracker/tracker_module.py
torchyolo/tracker/tracker_zoo.py
torchyolo/utils/__init__.py
torchyolo/utils/coco_classes.py
torchyolo/utils/config_utils.py
torchyolo/utils/dataset.py
torchyolo/utils/download.py
torchyolo/utils/file_utils.py
torchyolo/utils/load_config.py
torchyolo/utils/object_vis.py