Metadata-Version: 2.1
Name: torchyolo
Version: 1.3.0
Summary: PyTorch implementation of YOLOv5, YOLOv6, YOLOv7, YOLOv8
Home-page: https://github.com/kadirnar/torchyolo
Author: kadirnar
License: GPL-3.0
Keywords: machine-learning,deep-learning,pytorch,vision,yolov6,yolox,object-detection,yolov7,detector,yolov5
Classifier: Development Status :: 5 - Production/Stable
Classifier: Operating System :: OS Independent
Classifier: Intended Audience :: Developers
Classifier: Intended Audience :: Science/Research
Classifier: Programming Language :: Python :: 3
Classifier: Programming Language :: Python :: 3.7
Classifier: Programming Language :: Python :: 3.8
Classifier: Programming Language :: Python :: 3.9
Classifier: Topic :: Software Development :: Libraries
Classifier: Topic :: Software Development :: Libraries :: Python Modules
Classifier: Topic :: Education
Classifier: Topic :: Scientific/Engineering
Classifier: Topic :: Scientific/Engineering :: Artificial Intelligence
Requires-Python: >=3.6
Provides-Extra: tests
Provides-Extra: dev
License-File: LICENSE
